{"USD": [{"security": "PDD", "shares": 2918.879, "average_price": 107.84, "total_cost": 314771.91136}, {"security": "VT", "shares": 2601.642, "average_price": 95.65, "total_cost": 248847.0573}, {"security": "GOOG", "shares": 888.544, "average_price": 188.65, "total_cost": 167623.8256}, {"security": "ANET", "shares": 2419.55041, "average_price": 62.507369, "total_cost": 151239.73029197127}], "CNY": [{"security": "PDD", "shares": 2918.879, "average_price": 743.17936, "total_cost": 2169250.6271374403}, {"security": "VT", "shares": 2601.642, "average_price": 659.171975, "total_cost": 1714929.49538295}, {"security": "GOOG", "shares": 888.544, "average_price": 1300.081475, "total_cost": 1155179.5941224}, {"security": "ANET", "shares": 2419.55041, "average_price": 430.76953346349995, "total_cost": 1042268.6013071199}], "JPY": [{"security": "PDD", "shares": 2918.879, "average_price": 17210.0782992, "total_cost": 50234136.135890596}, {"security": "VT", "shares": 2601.642, "average_price": 15264.68832825, "total_cost": 39713254.27168498}, {"security": "GOOG", "shares": 888.544, "average_price": 30106.465793249998, "total_cost": 26750919.541797526}, {"security": "ANET", "shares": 2419.55041, "average_price": 9975.488823877844, "total_cost": 24136198.073764052}], "KRW": [{"security": "PDD", "shares": 2918.879, "average_price": 163372.20271584002, "total_cost": 476863691.6910084}, {"security": "VT", "shares": 2601.642, "average_price": 144904.96281315002, "total_cost": 376990837.2631292}, {"security": "GOOG", "shares": 888.544, "average_price": 285795.30825615, "total_cost": 253941706.37915257}, {"security": "ANET", "shares": 2419.55041, "average_price": 94695.53560368891, "total_cost": 229120621.9950751}]}