{
    "symbol": "PDD",
    "name": "Pinduoduo",
    "meta": {
        "schemaVersion": "1.1.0",
        "asOf": "2026-02-20T07:59:55.739546+00:00",
        "timezone": "UTC",
        "source": "analysis-sync"
    },
    "model": {
        "version": "1.0.0",
        "engine": {
            "type": "fermat-pascal-kelly",
            "useMonteCarlo": false,
            "paths": 10000,
            "useBayesianUpdate": false
        },
        "preferences": {
            "horizon": 5,
            "benchmark": {
                "type": "annualReturn",
                "value": 0.065,
                "name": "SP500"
            },
            "kellyScale": 0.5,
            "targetCagr": 0.12,
            "overrides": {}
        }
    },
    "market": {
        "forwardEps": 12.5808,
        "pe": 10.2052,
        "forwardPe": 8.1036,
        "beta": -0.014,
        "marketCap": 144732946432.0,
        "enterpriseValue": 157541335040.0,
        "ebitda": 93147258880.0,
        "currency": "USD",
        "fiftyTwoWeekHigh": 139.41,
        "fiftyTwoWeekLow": 87.11,
        "marketDataUpdatedAt": "2026-02-20T07:59:55.659195+00:00",
        "evToEbitda": 1.6913,
        "eps": 9.99,
        "price": 101.95,
        "fiftyDayAverage": 110.1544,
        "twoHundredDayAverage": 116.3344,
        "averageVolume": 8719546.0,
        "averageDailyVolume10Day": 7174320.0
    },
    "risk": {
        "volatility": 0.3829,
        "estimateSource": "historical",
        "correlations": null
    },
    "position": {
        "shares": 2644.573,
        "currentWeight": null,
        "targetWeight": null,
        "maxKellyWeight": null,
        "portfolioId": null,
        "constraints": {
            "minWeight": 0.0,
            "maxWeight": 0.3
        }
    },
    "scenarios": [
        {
            "id": "bull",
            "name": "Bull",
            "prob": 0.25,
            "growth": {
                "epsCagr": 0.18,
                "epsCagrSigma": null
            },
            "valuation": {
                "exitPe": 18.0,
                "exitPeSigma": null
            },
            "notes": "Pinduoduo dominates domestic value e-commerce, monetization improves, and Temu becomes a profitable global platform."
        },
        {
            "id": "base",
            "name": "Base",
            "prob": 0.5,
            "growth": {
                "epsCagr": 0.12,
                "epsCagrSigma": null
            },
            "valuation": {
                "exitPe": 15.0,
                "exitPeSigma": null
            },
            "notes": "Steady growth: Pinduoduo matures yet grows with China, Temu achieves mixed success and roughly breakeven economics."
        },
        {
            "id": "bear",
            "name": "Bear",
            "prob": 0.2,
            "growth": {
                "epsCagr": 0.03,
                "epsCagrSigma": null
            },
            "valuation": {
                "exitPe": 10.0,
                "exitPeSigma": null
            },
            "notes": "Moat erosion: domestic growth stalls, Temu struggles to reach profitability, margins compress under subsidies and regulation."
        }
    ],
    "derived": {
        "expectedCagr": null,
        "expectedMultiple": null,
        "fairValueRange": null,
        "kelly": {
            "fullKelly": null,
            "scaledKelly": null
        }
    }
}
